cdktf_cdktf_provider_opc/__init__.py
cdktf_cdktf_provider_opc/py.typed
cdktf_cdktf_provider_opc/_jsii/__init__.py
cdktf_cdktf_provider_opc/_jsii/provider-opc@8.0.1.jsii.tgz
cdktf_cdktf_provider_opc/compute_acl/__init__.py
cdktf_cdktf_provider_opc/compute_image_list/__init__.py
cdktf_cdktf_provider_opc/compute_image_list_entry/__init__.py
cdktf_cdktf_provider_opc/compute_instance/__init__.py
cdktf_cdktf_provider_opc/compute_ip_address_association/__init__.py
cdktf_cdktf_provider_opc/compute_ip_address_prefix_set/__init__.py
cdktf_cdktf_provider_opc/compute_ip_address_reservation/__init__.py
cdktf_cdktf_provider_opc/compute_ip_association/__init__.py
cdktf_cdktf_provider_opc/compute_ip_network/__init__.py
cdktf_cdktf_provider_opc/compute_ip_network_exchange/__init__.py
cdktf_cdktf_provider_opc/compute_ip_reservation/__init__.py
cdktf_cdktf_provider_opc/compute_machine_image/__init__.py
cdktf_cdktf_provider_opc/compute_orchestrated_instance/__init__.py
cdktf_cdktf_provider_opc/compute_route/__init__.py
cdktf_cdktf_provider_opc/compute_sec_rule/__init__.py
cdktf_cdktf_provider_opc/compute_security_application/__init__.py
cdktf_cdktf_provider_opc/compute_security_association/__init__.py
cdktf_cdktf_provider_opc/compute_security_ip_list/__init__.py
cdktf_cdktf_provider_opc/compute_security_list/__init__.py
cdktf_cdktf_provider_opc/compute_security_protocol/__init__.py
cdktf_cdktf_provider_opc/compute_security_rule/__init__.py
cdktf_cdktf_provider_opc/compute_snapshot/__init__.py
cdktf_cdktf_provider_opc/compute_ssh_key/__init__.py
cdktf_cdktf_provider_opc/compute_storage_attachment/__init__.py
cdktf_cdktf_provider_opc/compute_storage_volume/__init__.py
cdktf_cdktf_provider_opc/compute_storage_volume_snapshot/__init__.py
cdktf_cdktf_provider_opc/compute_vnic_set/__init__.py
cdktf_cdktf_provider_opc/compute_vpn_endpoint_v2/__init__.py
cdktf_cdktf_provider_opc/data_opc_compute_image_list_entry/__init__.py
cdktf_cdktf_provider_opc-8.0.1.dist-info/LICENSE
cdktf_cdktf_provider_opc-8.0.1.dist-info/METADATA
cdktf_cdktf_provider_opc-8.0.1.dist-info/WHEEL
cdktf_cdktf_provider_opc-8.0.1.dist-info/top_level.txt
cdktf_cdktf_provider_opc-8.0.1.dist-info/RECORD
